telegram_logger_client/__init__.py
telegram_logger_client/__main__.py
telegram_logger_client/_constants.py
telegram_logger_client/_logging_handler.py
telegram_logger_client/_telegram_logger_client.py
telegram_logger_client-0.2.2.dist-info/METADATA
telegram_logger_client-0.2.2.dist-info/WHEEL
telegram_logger_client-0.2.2.dist-info/entry_points.txt
telegram_logger_client-0.2.2.dist-info/licenses/LICENSE
telegram_logger_client-0.2.2.dist-info/RECORD
