Metadata-Version: 2.3
Name: telegram-logger-client
Version: 0.2.2
Summary: A Python client for the telegram-logger service
Project-URL: Homepage, https://github.com/psyb0t/py-telegram-logger-client
Project-URL: Issues, https://github.com/psyb0t/py-telegram-logger-client/issues
Author-email: Ciprian Mandache <psyb0t@51k.eu>
License-File: LICENSE
Classifier: Operating System :: OS Independent
Classifier: Programming Language :: Python :: 3
Requires-Python: >=3.6
Requires-Dist: requests>=2.32.3
